README.md
setup.py
TOPSIS_Vedant_101803329.egg-info/PKG-INFO
TOPSIS_Vedant_101803329.egg-info/SOURCES.txt
TOPSIS_Vedant_101803329.egg-info/dependency_links.txt
TOPSIS_Vedant_101803329.egg-info/top_level.txt
topsis_cal/__init__.py
topsis_cal/topsiscode.py