Metadata-Version: 2.1
Name: TOPSIS-Vedant-101803329
Version: 1
Summary: Topsis Calculator
Home-page: UNKNOWN
Author: Vedant Gupta
Author-email: vgupta2_be18@thapar.edu
License: UNKNOWN
Platform: UNKNOWN
Classifier: Programming Language :: Python :: 3
Classifier: License :: OSI Approved :: MIT License
Classifier: Operating System :: OS Independent
